COPYING.txt
MANIFEST.in
README.rst
setup.py
telnetsrv3/__init__.py
telnetsrv3/evtlet.py
telnetsrv3/green.py
telnetsrv3/paramiko_ssh.py
telnetsrv3/telnetsrvlib3.py
telnetsrv3/threaded.py
telnetsrv3.egg-info/PKG-INFO
telnetsrv3.egg-info/SOURCES.txt
telnetsrv3.egg-info/dependency_links.txt
telnetsrv3.egg-info/requires.txt
telnetsrv3.egg-info/top_level.txt