Metadata-Version: 2.1
Name: telnetsrv3
Version: 0.5.4
Summary: Telnet server handler library
Home-page: https://github.com/ianepperson/telnetsrvlib
Author: Ian Epperson
Author-email: ian@epperson.com
Keywords: gevent,telnet,server
Classifier: Programming Language :: Python
Classifier: Development Status :: 4 - Beta
Classifier: Environment :: Other Environment
Classifier: Intended Audience :: Developers
Classifier: License :: OSI Approved :: GNU Library or Lesser General Public License (LGPL)
Classifier: Operating System :: OS Independent
Classifier: Topic :: Software Development :: Libraries :: Python Modules
Classifier: Topic :: Communications
Classifier: Topic :: Communications :: BBS
Classifier: Topic :: System :: Shells
Classifier: Topic :: Terminals
Classifier: Topic :: Terminals :: Telnet
Provides-Extra: green
Provides-Extra: ssh
License-File: COPYING.txt
